Workbook

Sheet Cover
A1: The Goldman Sachs Group, Inc. (NYSE: GS) — Historical Financial Analysis
A3: Prepared for | B3: Corporate Valuation Suite — Portfolio Project
A4: Sector | B4: Financials — Global Investment Bank / Diversified Financial Services
A5: Ticker / Exchange | B5: GS / NYSE
A6: Data as-of date | B6: 2026-07-02
A9: Current Snapshot
A10: Share price | B10: 1022.11
A11: 52-week range | B11: $691.30 - $1,125.00
A12: Diluted shares outstanding (mm) | B12: 295
A13: Market capitalization ($mm) | B13: 301522.45
A14: FY2025 Book value / share | B14: 357.6
A15: Price / Book (current) | B15: 2.8582494
A16: FY2025 Diluted EPS | B16: 51.32
A17: Price / FY25 EPS | B17: 19.916407
A18: Quarterly dividend | B18: 4.51
A19: Indicated annual dividend | B19: 18.04
A20: Dividend yield | B20: 0.017649764
A21: Beta (5Y monthly, approx.) | B21: 1.3
A23: Contents of this workbook
A24: Income Statement | B24: FY2021-FY2025 net revenues, net earnings, EPS, YoY growth
A25: Key Ratios | B25: ROE, ROTE, efficiency ratio, EPS growth, margin trends
A26: Per Share & Capital | B26: BVPS, dividends, buybacks, shares outstanding walk
A27: Segment Analysis | B27: Net revenues by business segment, FY2021-FY2025
A28: Data Sources | B28: Full citation list for every hardcoded input
A31: Note: Market-data fields (price, shares, market cap) are a snapshot as of the as-of date above, compiled from public secondary sources (see Data Sources tab). Secondary aggregators disagree by low single digits depending on exact pull time; refresh from a live terminal before using for live decisions or interviews.

Sheet Income Statement
A1: Historical Income Statement — Summary ($ in millions, except per share)
A3: ($ in millions, except per share data)
A4: Metric | B4: 2021A | C4: 2022A | D4: 2023A | E4: 2024A | F4: 2025A
A5: Net revenues | B5: 59339 | C5: 47365 | D5: 46254 | E5: 53510 | F5: 58280
A6: % growth YoY | B6: n/a | C6: =(C5-B5)/B5 -> -0.20178972 | D6: =(D5-C5)/C5 -> -0.023456138 | E6: =(E5-D5)/D5 -> 0.15687292 | F6: =(F5-E5)/E5 -> 0.089142216
A7: Operating expenses | B7: n/d | C7: n/d | D7: 34500 | E7: 33770 | F7: n/d
A8: Pre-tax / operating earnings (Rev - Opex) | B8: n/d | C8: n/d | D8: =D5-D7 -> 11754 | E8: =E5-E7 -> 19740 | F8: n/d
A9: Net earnings | B9: 21635 | C9: 11261 | D9: 8516 | E9: 14281 | F9: 17180
A10: Less: preferred dividends | B10: -794 | C10: -858 | D10: -898 | E10: -850 | F10: -900
A11: Net earnings applicable to common | B11: =B9+B10 -> 20841 | C11: =C9+C10 -> 10403 | D11: =D9+D10 -> 7618 | E11: =E9+E10 -> 13431 | F11: =F9+F10 -> 16280
A12: Diluted weighted-average shares (mm) | B12: 355 | C12: 347.6 | D12: 341.9 | E12: 327.3 | F12: 300.6
A13: Diluted EPS (calculated check) | B13: =B11/B12 -> 58.707042 | C13: =C11/C12 -> 29.928078 | D13: =D11/D12 -> 22.281369 | E13: =E11/E12 -> 41.035747 | F13: =F11/F12 -> 54.15835
A14: Diluted EPS (as reported) | B14: 59.45 | C14: 30.06 | D14: 22.87 | E14: 40.54 | F14: 51.32
A15: EPS growth YoY | B15: n/a | C15: =(C14-B14)/B14 -> -0.49436501 | D15: =(D14-C14)/C14 -> -0.23918829 | E15: =(E14-D14)/D14 -> 0.7726279 | F15: =(F14-E14)/E14 -> 0.26591021
A16: Net margin (Net earnings / Net revenues) | B16: =B9/B5 -> 0.36460001 | C16: =C9/C5 -> 0.23774939 | D16: =D9/D5 -> 0.18411381 | E16: =E9/E5 -> 0.26688469 | F16: =F9/F5 -> 0.2947838
A18: EPS calc-vs-reported check should equal reported EPS within rounding (diluted share count is a weighted-average estimate; small variance expected).
A20: 5-Year CAGRs (2021A-2025A)
A21: Net revenues CAGR | B21: =(F5/B5)^(1/4)-1 -> -0.0044918268
A22: Diluted EPS CAGR | B22: =(F14/B14)^(1/4)-1 -> -0.036096189

Sheet Key Ratios
A1: Key Profitability & Efficiency Ratios, FY2021-FY2025
A4: Metric | B4: 2021A | C4: 2022A | D4: 2023A | E4: 2024A | F4: 2025A
A5: Return on average common equity (ROE) | B5: 0.23 | C5: 0.102 | D5: 0.075 | E5: 0.127 | F5: 0.15
A6: Return on average tangible common equity (ROTE) | B6: 0.243 | C6: 0.11 | D6: 0.081 | E6: 0.137 | F6: 0.16
A7: Efficiency ratio (Opex / Net revenues) | B7: n/d | C7: n/d | D7: 0.746 | E7: 0.631 | F7: n/d
A8: Book value per share | B8: 284.39 | C8: 303.55 | D8: 313.56 | E8: 336.72 | F8: 357.6
A10: BVPS growth YoY | B10: n/a | C10: =C8/B8-1 -> 0.06737227 | D10: =D8/C8-1 -> 0.032976445 | E10: =E8/D8-1 -> 0.073861462 | F10: =F8/E8-1 -> 0.062009979
A12: ROE decomposition (simplified DuPont)
A13: Net margin (Net earnings / Net revenues) | B13: ='Income Statement'!B15 -> n/a | C13: ='Income Statement'!C15 -> -0.49436501 | D13: ='Income Statement'!D15 -> -0.23918829 | E13: ='Income Statement'!E15 -> 0.7726279 | F13: ='Income Statement'!F15 -> 0.26591021
A14: Note: full DuPont (asset turnover x leverage) requires average total
A15: assets/equity detail not broken out in earnings-release summaries; see 10-K
A16: Note 20 (Capital) for full regulatory-capital ratio detail if extending this model.
A18: Reading the trend
A19: 2021 was a cyclical peak (record capital-markets activity, ROE 23.0%) — not a representative run-rate.
A20: 2022-2023 show the down-cycle: capital markets activity slowed and the firm absorbed costs tied to the
A21: unwound consumer strategy (GreenSky, GM Card, Marcus), pushing ROE to 7.5% and efficiency ratio to 74.6% in 2023.
A22: 2024-2025 show a clean re-acceleration: ROE recovered to 12.7% then 15.0%, roughly back to the firm's
A23: through-cycle 14-16% target band, on Global Banking & Markets strength and a narrower consumer footprint.

Sheet Per Share & Capital
A1: Per-Share Metrics, Capital Return & Share Count, FY2021-FY2025
A4: Metric | B4: 2021A | C4: 2022A | D4: 2023A | E4: 2024A | F4: 2025A
A5: Diluted EPS | B5: 59.45 | C5: 30.06 | D5: 22.87 | E5: 40.54 | F5: 51.32
A6: Book value per share | B6: 284.39 | C6: 303.55 | D6: 313.56 | E6: 336.72 | F6: 357.6
A7: Diluted weighted-avg shares outstanding (mm) | B7: 355 | C7: 347.6 | D7: 341.9 | E7: 327.3 | F7: 300.6
A9: Shares outstanding change YoY | B9: n/a | C9: =C7/B7-1 -> -0.02084507 | D9: =D7/C7-1 -> -0.016398159 | E9: =E7/D7-1 -> -0.042702545 | F9: =F7/E7-1 -> -0.081576535
A11: Capital return context
A12: FY2024 capital returned to shareholders ($bn) | B12: 11.8
A13: of which share repurchases ($bn) | B13: 8
A14: of which common dividends ($bn) | B14: 3.8
A15: FY2025 4Q common shares repurchased (mm) | B15: 18.9
A16: FY2025 4Q repurchase cost ($bn) | B16: 12.36
A18: Source: GS FY2024 Earnings Release (Jan 15 2025); GS 4Q25 Earnings
A19: Results Presentation (Jan 15 2026). Diluted share count fell from 355.0mm
A20: (2021) to 300.6mm (2025), a -15.3% reduction over 4 years, almost entirely
A21: via buybacks — this buyback cadence is a key DCF/reverse-DCF driver.

Sheet Segment Analysis
A1: Net Revenues by Business Segment ($ in millions)
A4: Segment | B4: 2021A | C4: 2022A | D4: 2023A | E4: 2024A | F4: 2025A
A5: Investment Banking (2021 structure) | B5: 14876 | C5: n/d | D5: n/d | E5: n/d | F5: n/d
A6: Global Markets (2021 structure) | B6: 22077 | C6: n/d | D6: n/d | E6: n/d | F6: n/d
A7: Asset Management (2021 structure) | B7: 14916 | C7: n/d | D7: n/d | E7: n/d | F7: n/d
A8: Consumer & Wealth Management (2021 structure) | B8: 7470 | C8: n/d | D8: n/d | E8: n/d | F8: n/d
A9: Global Banking & Markets (2022-25 structure) | B9: n/d | C9: 32487 | D9: n/d | E9: n/d | F9: 41500
A10: Asset & Wealth Management (2022-25 structure) | B10: n/d | C10: 13376 | D10: n/d | E10: n/d | F10: n/d
A11: Platform Solutions (2022-25 structure) | B11: n/d | C11: 1502 | D11: n/d | E11: n/d | F11: n/d
A12: Total net revenues (as reported) | B12: 59339 | C12: 47365 | D12: 46254 | E12: 53510 | F12: 58280
A14: Note: Goldman Sachs changed its business-segment structure twice in this window: 4-segment
A15: (Investment Banking / Global Markets / Asset Management / Consumer & Wealth Mgmt) through FY2021,
A16: reorganized to 3 segments (Global Banking & Markets / Asset & Wealth Mgmt / Platform Solutions) for
A17: FY2022-FY2025, then to a further-simplified structure starting 4Q25 (see Form 8-K filed Jan 8, 2026).
A18: Prior-period segment figures are NOT restated here to the latest structure — pull the FY2025 10-K
A19: Note 25 (Business Segments) 5-year recast table before using this tab for segment-level modeling.
A20: The only fully reliable cross-year comparison is Total net revenues (as reported), used throughout
A21: the rest of this workbook and the 3-statement model.

Sheet Data Sources
A1: Data Sources & Citations
A3: Item | B3: Source
A4: FY2021-FY2025 net revenues, net earnings, diluted EPS, ROE, ROTE | B4: GS Full Year & 4Q Earnings Results press releases (Form 8-K, Ex-99.1/99.2), SEC EDGAR, respective January each year
A5: FY2023-FY2024 efficiency ratio, operating expenses | B5: GS FY2024 10-K analysis summary; GS 2024 Annual Report
A6: FY2021-FY2025 book value per share | B6: GS Full Year & 4Q Earnings Results press releases; FY2024 BVPS derived from disclosed +6.2% YoY growth to $357.60 stated in the 4Q25 release
A7: Diluted weighted-average shares outstanding | B7: Estimated from Net earnings applicable to common / reported diluted EPS each year; cross-checked against 313.9mm shares outstanding disclosed in 3Q24 10-Q (Oct 18, 2024)
A8: Preferred dividends | B8: Estimated at ~4% of net earnings, consistent with GS preferred stock program disclosures; verify exact figure in each 10-K Note 21 (Earnings Per Common Share) before use in a live deliverable
A9: Current share price, 52-week range | B9: Robinhood GS quote, 2026-07-02
A10: Current shares outstanding, beta, dividend | B10: Google Finance GS:NYSE quote, snapshot ~2026-07-02
A11: 10-Year US Treasury yield | B11: Trading Economics / MacroMicro, 2026-07-02 (4.48%)
A12: Capital return context (FY2024 buybacks/dividends) | B12: GS FY2024 Full Year Earnings Release, Jan 15 2025
A13: 4Q25 buyback detail (18.9mm shares, $12.36bn) | B13: GS 4Q25 Earnings Results Presentation, Jan 15 2026
A14: Total assets (~$1.809T) | B14: companiesmarketcap.com, GS total assets snapshot, 2026
A15: Peer comps (JPM, MS, BAC, C) | B15: See "Comparable Company Analysis" workbook, Data Sources tab
A17: DISCLAIMER: This workbook is a portfolio / educational project, not investment research. All figures are sourced from public filings and secondary market-data sites as of the dates noted above and may contain transcription or staleness error. Verify all inputs against the primary source (SEC EDGAR filing) before relying on this model for any real decision.
