Workbook

Sheet Trading Comps
A1: Comparable Company Analysis — Large-Cap US Banks / Global Investment Banks
A3: Market data snapshot as of 2026-07-02; see Data Sources tab for per-company citations
A5: Company | B5: Ticker | C5: Price | D5: Diluted Shares (mm) | E5: Market Cap ($mm) | F5: BVPS ($) | G5: P / B | H5: TTM EPS ($) | I5: P / E | J5: ROE (ttm/most recent)
A6: The Goldman Sachs Group, Inc. | B6: GS | C6: 1022.11 | D6: 295 | E6: =C6*D6 -> 301522.45 | F6: 357.6 | G6: =C6/F6 -> 2.8582494 | H6: 54.72 | I6: =C6/H6 -> 18.678911 | J6: 0.15
A7: JPMorgan Chase & Co. | B7: JPM | C7: 333.7 | D7: 2680 | E7: =C7*D7 -> 894316 | F7: n/d | G7: n/d | H7: 20.88 | I7: =C7/H7 -> 15.981801 | J7: 0.1646
A8: Morgan Stanley | B8: MS | C8: 212.68 | D8: 1320 | E8: =C8*D8 -> 280737.6 | F8: n/d | G8: n/d | H8: 12.69 | I8: =C8/H8 -> 16.759653 | J8: n/d
A9: Bank of America Corp. | B9: BAC | C9: 55.16 | D9: 7096.6 | E9: =C9*D9 -> 391448.46 | F9: n/d | G9: n/d | H9: n/d | I9: n/d | J9: n/d
A10: Citigroup Inc. | B10: C | C10: 140 | D10: 1705.6 | E10: =C10*D10 -> 238784 | F10: 112.22 | G10: =C10/F10 -> 1.2475495 | H10: n/d | I10: n/d | J10: 0.0765
A12: Peer mean | G12: =AVERAGE(G7:G10) -> 1.2475495 | I12: =AVERAGE(I7:I10) -> 16.370727 | J12: =AVERAGE(J7:J10) -> 0.12055
A13: Peer median | G13: =MEDIAN(G7:G10) -> 1.2475495 | I13: =MEDIAN(I7:I10) -> 16.370727 | J13: =MEDIAN(J7:J10) -> 0.12055
A15: Peer set: JPMorgan Chase, Morgan Stanley, Bank of America, Citigroup -- the standard large-cap US
A16: bank / global-markets peer group GS itself references in its own investor presentations (GS 2024
A17: Annual Report explicitly names MS, JPM, BAC, C as its primary total-shareholder-return peer set).
A18: 'n/d' = not directly sourced for this snapshot; see Data Sources tab. P/E and P/B use TTM figures
A19: where available, which will differ modestly from single-fiscal-year (FY2025A) multiples due to
A20: quarter-mix effects -- treat all multiples here as directional, not decimal-precise.

Sheet Implied Valuation
A1: Implied GS Value per Share — Applying Peer Multiples to GS Financials
A3: GS Inputs
A4: GS Book value per share ($) | B4: ='Trading Comps'!F6 -> 357.6
A5: GS TTM EPS ($) | B5: ='Trading Comps'!H6 -> 54.72
A6: GS current share price ($) | B6: ='Trading Comps'!C6 -> 1022.11
A8: Peer Multiples Applied to GS
A9: Method | B9: Peer multiple | C9: Applied to GS | D9: Implied GS Price/Share ($)
A10: P/B, peer mean | B10: ='Trading Comps'!G12 -> 1.2475495 | C10: =B4 -> 357.6 | D10: =B10*C10 -> 446.12369
A11: P/B, peer median | B11: ='Trading Comps'!G13 -> 1.2475495 | C11: =B4 -> 357.6 | D11: =B11*C11 -> 446.12369
A12: P/E, peer mean | B12: ='Trading Comps'!I12 -> 16.370727 | C12: =B5 -> 54.72 | D12: =B12*C12 -> 895.80618
A13: P/E, peer median | B13: ='Trading Comps'!I13 -> 16.370727 | C13: =B5 -> 54.72 | D13: =B13*C13 -> 895.80618
A15: Blended average of 4 methods above | D15: =AVERAGE(D10:D13) -> 670.96493
A16: Range: min - max of 4 methods | D16: =MIN(D10:D13)&" - $"&TEXT(MAX(D10:D13),"0.00") -> 446.123685617537 - $895.81
A18: Cross-Check vs. Current Price and DCF
A19: Comps-implied price (blended) vs. current price | B19: =D15/B6-1 -> -0.34354919
A20: DCF Base Case implied price/share (from DCF workbook) | B20: 631.24
A21: Source | B21: 'DCF and Reverse DCF' workbook, DCF Valuation tab, Base Case
A23: Reading across methods: the comps-implied price uses where the MARKET currently prices GS's peer
A24: set (JPM, MS, BAC, C) and asks 'if GS traded at the same multiple as its peers, what would it be
A25: worth?' -- a relative-value lens. The DCF asks an absolute-value question: 'given this cash-flow
A26: path and discount rate, what is GS intrinsically worth?' When the two disagree meaningfully (as
A27: they do here), the gap is usually explained by (a) the market pricing GS's superior ROE/ROTE
A28: profile at a premium multiple to peers, and/or (b) the DCF's discount rate or terminal growth
A29: being conservative relative to what the market is willing to pay. Both readings belong in the memo.
